tagnote/__init__.py
tagnote/tag.py
tagnote-4.3.0.dist-info/COPYING
tagnote-4.3.0.dist-info/METADATA
tagnote-4.3.0.dist-info/WHEEL
tagnote-4.3.0.dist-info/entry_points.txt
tagnote-4.3.0.dist-info/top_level.txt
tagnote-4.3.0.dist-info/RECORD
