Metadata-Version: 2.1
Name: tagnote
Version: 4.3.0
Summary: Minimalist note organization tool
Home-page: https://github.com/michael-ren/tagnote
Author: Michael Ren
Author-email: michael.ren@mailbox.org
License: GPLv3
Platform: UNKNOWN
Classifier: Programming Language :: Python :: 3
Classifier: Programming Language :: Python :: 3.5
Classifier: Programming Language :: Python :: 3.6
Classifier: Programming Language :: Python :: 3.7
Classifier: Environment :: Console
Classifier: License :: OSI Approved :: GNU General Public License v3 (GPLv3)
Classifier: Operating System :: POSIX
Classifier: Operating System :: Unix
Requires-Python: >=3.5
